LICENSE
README.md
setup.py
karuo/__init__.py
karuo/datadef.py
karuo/decorators.py
karuo.egg-info/PKG-INFO
karuo.egg-info/SOURCES.txt
karuo.egg-info/dependency_links.txt
karuo.egg-info/requires.txt
karuo.egg-info/top_level.txt
karuo/baiduai/__init__.py
karuo/baiduai/base.py
karuo/baiduai/error_code.py
karuo/baiduai/func_faces.py
karuo/baiduai/func_ocr.py
karuo/helpers/__init__.py
karuo/helpers/char_helper.py
karuo/helpers/date_helper.py
karuo/helpers/logger_helper.py
karuo/qywx/WXBizMsgCrypt.py
karuo/qywx/__init__.py
karuo/qywx/base.py
karuo/qywx/helper.py
karuo/qywx/ierror.py
karuo/qywx/provider.py
test/__init__.py
test/test_ai_face.py
test/test_ai_ocr.py
test/test_helpers.py
test/test_normal.py
test/test_qywx.py